LICENSE
README.md
setup.py
docs/usage.rst
lsqAxSI/__init__.py
lsqAxSI/default_values.py
lsqAxSI/lsq_aprecon.py
lsqAxSI/lsq_axsi.py
lsqAxSI/lsq_components.py
lsqAxSI/lsq_conjugate_gradients.py
lsqAxSI/lsq_trust_region.py
lsqAxSI/matrix_operations.py
lsqAxSI.egg-info/PKG-INFO
lsqAxSI.egg-info/SOURCES.txt
lsqAxSI.egg-info/dependency_links.txt
lsqAxSI.egg-info/requires.txt
lsqAxSI.egg-info/top_level.txt
scripts/lsq_AxSI.py